{
  "drops": [
	{
      "id": 563,
      "count": [
        40,
        45
      ],
      "chance": 4
    },
	{
      "id": 560,
      "count": [
        40,
        45
      ],
      "chance": 4
    },
	{
      "id": 561,
      "count": [
        65
      ],
      "chance": 4
    },
	{
      "id": 892,
      "count": [
        42
      ],
      "chance": 4
    },
	{
      "id": 1623,
      "count": [
        1
      ],
      "chance": 2
    },
	{
      "id": 1621,
      "count": [
        1
      ],
      "chance": 2
    },
	{
      "id": 1619,
      "count": [
        1
      ],
      "chance": 3
    },
	{
      "id": 1617,
      "count": [
        1
      ],
      "chance": 3
    },
	{
      "id": 1615,
      "count": [
        1
      ],
      "chance": 6
    },
	{
      "id": 443,
      "count": [
        50,
		100
      ],
      "chance": 6
    },
	{
      "id": 1452,
      "count": [
        1
      ],
      "chance": 2
    },
	{
      "id": 1462,
      "count": [
        1
      ],
      "chance": 3
    },
	{
      "id": 985,
      "count": [
        1
      ],
      "chance": 3
    },
	{
      "id": 987,
      "count": [
        1
      ],
      "chance": 3
    },
	{
      "id": 995,
      "count": [
        1000,
        3000
      ],
      "chance": 4
    },
	{
      "id": 830,
      "count": [
        50
      ],
      "chance": 3
    },
	{
      "id": 1247,
      "count": [
        1
      ],
      "chance": 6
    },
	{
      "id": 1319,
      "count": [
        1
      ],
      "chance": 6
    },
	{
      "id": 1373,
      "count": [
        1
      ],
      "chance": 6
    },
	{
      "id": 1149,
      "count": [
        1
      ],
      "chance": 6
    },
	{
      "id": 1201,
      "count": [
        1
      ],
      "chance": 5
    },
	{
      "id": 2366,
      "count": [
        1
      ],
      "chance": 5
    },
	{
      "id": 1249,
      "count": [
        1
      ],
      "chance": 5
    },
	{
      "id": 1631,
      "count": [
        1
      ],
      "chance": 5
    }
  ]
}